filecombinator/__init__.py
filecombinator/_version.py
filecombinator/cli.py
filecombinator/py.typed
filecombinator/core/__init__.py
filecombinator/core/banner.py
filecombinator/core/banner.txt
filecombinator/core/combinator.py
filecombinator/core/config.py
filecombinator/core/config.yaml
filecombinator/core/console.py
filecombinator/core/exceptions.py
filecombinator/core/file_utils.py
filecombinator/core/formatting.py
filecombinator/core/logging.py
filecombinator/core/models.py
filecombinator/core/templates/ai_instructions.md
filecombinator/processors/__init__.py
filecombinator/processors/content.py
filecombinator/processors/directory.py
filecombinator-0.4.1.dist-info/LICENSE
filecombinator-0.4.1.dist-info/METADATA
filecombinator-0.4.1.dist-info/WHEEL
filecombinator-0.4.1.dist-info/entry_points.txt
filecombinator-0.4.1.dist-info/top_level.txt
filecombinator-0.4.1.dist-info/RECORD
