Metadata-Version: 2.1
Name: filecombinator
Version: 0.4.1
Summary: A tool to combine multiple files while preserving directory structure
Author: Peiman Khorramshahi
Author-email: peiman@khorramshahi.com
License: MIT
Classifier: Development Status :: 3 - Alpha
Classifier: Intended Audience :: Developers
Classifier: License :: OSI Approved :: MIT License
Classifier: Programming Language :: Python :: 3
Classifier: Programming Language :: Python :: 3.11
Requires-Python: >=3.11,<3.12
License-File: LICENSE
Requires-Dist: python-magic>=0.4.27
Requires-Dist: click>=8.1.7
Requires-Dist: rich>=13.9.4
